setuptools_cuda_cpp/__init__.py
setuptools_cuda_cpp/build_ext.py
setuptools_cuda_cpp/extension.py
setuptools_cuda_cpp/find_cuda.py
setuptools_cuda_cpp/ninja_build.py
setuptools_cuda_cpp/nvml.py
setuptools_cuda_cpp/utils.py
setuptools_cuda_cpp-0.1.8.dist-info/entry_points.txt
setuptools_cuda_cpp-0.1.8.dist-info/LICENSE
setuptools_cuda_cpp-0.1.8.dist-info/WHEEL
setuptools_cuda_cpp-0.1.8.dist-info/METADATA
setuptools_cuda_cpp-0.1.8.dist-info/RECORD
