Metadata-Version: 2.1
Name: setuptools-cuda-cpp
Version: 0.1.8
Summary: Module that extends setuptools functionality for building hybrid C++ and CUDA extension for Python wrapper modules.
Keywords: cuda,extension,compilation,compile,cpp,c++,cross,ext,setuptools,wrapper
Author-email: "Rafael J. Vicente" <rafaelj.vicente@gmail.com>
Requires-Python: >=3.6
Classifier: License :: OSI Approved :: MIT License
Classifier: Development Status :: 4 - Beta
Classifier: Programming Language :: Python
Classifier: Programming Language :: Python :: 3.6
Classifier: Programming Language :: Python :: 3.7
Classifier: Programming Language :: Python :: 3.8
Classifier: Programming Language :: Python :: 3.9
Classifier: Programming Language :: Python :: 3.10
Classifier: Programming Language :: Python :: 3.11
Classifier: Programming Language :: Python :: Implementation :: CPython
Classifier: Programming Language :: Python :: Implementation :: PyPy
Requires-Dist: setuptools
Requires-Dist: nvidia-ml-py
Project-URL: Documentation, https://github.com/RafaelJVicente/setuptools-cuda-cpp#readme
Project-URL: Issues, https://github.com/RafaelJVicente/setuptools-cuda-cpp/issues
Project-URL: Source, https://github.com/RafaelJVicente/setuptools-cuda-cpp
